src/ext_fifo_tx.v
`timescale 1ns / 1ps
//////////////////////////////////////////////////////////////////////////////////
// Company: Transbit Sp. z o.o.
// Engineer: MB, GM
//
// Create Date: 07/12/2022 09:44:09 AM
// Design Name: Xilinx MPSoC GEM External FIFO Interface - Tx
// Module Name: ext_fifo_tx
// Project Name:
// Target Devices:
// Tool Versions:
// Description: The transmitter module of External FIFO IP.
//
// Dependencies:
//
// Revision:
// 1.01 [MB] - File Created
// 1.02 [GM] - Changed signal names to standard; chenged handshaking
// Additional Comments:
//
//////////////////////////////////////////////////////////////////////////////////


module ext_fifo_tx (

    output wire [7:0] data_o,
    output reg data_ready_o,
    output reg data_valid_o,
    output reg sop_o,
    output reg eop_o,
    output reg err_o,
    output reg underflow_o,
    output reg flushed_o,
    output reg control_o,
    output reg dma_tx_status_tog_o,
    input wire dma_tx_end_tog_i,
    input wire rd_i,
    input wire [3:0] status_i,

    // AXI4-Stream 
    input wire [7:0] s_axis_tdata,
    input wire [7:0] s_axis_tid,
    input wire [7:0] s_axis_tdest,
    output wire s_axis_tready,
    input wire s_axis_tkeep,
    input wire s_axis_tvalid,
    input wire s_axis_tlast,
    input wire s_axis_tuser,
    input wire rstn,
    input wire clk
);

  reg packet;
  /* reg dma_end_tog_prev; */

  /* GM patch */
  /* incorrect handshaking */

  assign s_axis_tready = rd_i;
  assign data_o = s_axis_tdata;

  always @(posedge clk) begin

    // Reset
    if (rstn == 1'b0) begin
      err_o <= 1'b0;
      control_o <= 1'b0;
      underflow_o <= 1'b0;
      flushed_o <= 1'b0;
      dma_tx_status_tog_o <= 1'b0;
      packet <= 1'b0;
      sop_o <= 1'b0;
      eop_o <= 1'b0;
    end else begin 

      // Signal MAC that data is ready to send
      if (packet == 1'b0)
        data_ready_o <= s_axis_tvalid;
      else 
        data_ready_o <= 1'b0;

      data_valid_o = rd_i & s_axis_tvalid;

      // If the FIFO is empty, and a read signal has been asserted, set underflow
      if (status_i[3] == 1'b1) underflow_o <= 1'b1;
      else underflow_o <= 1'b0;


      // On setting o_underflow, or receiving status, assert o_flushed
      if (underflow_o == 1'b1 || status_i != 4'b0) flushed_o <= 1'b1;
      else flushed_o <= 1'b0;

      // o_dma_status_tog has to be asserted after i_dma_end_tog is received
      if (dma_tx_end_tog_i == 1'b1 || status_i[2] == 1'b1) dma_tx_status_tog_o <= 1'b1;
      else dma_tx_status_tog_o <= 1'b0;

      if ((s_axis_tvalid == 1'b1) && (s_axis_tready == 1'b1) && (packet == 1'b0))
        packet <= 1'b1;
      else if ((s_axis_tvalid == 1'b1) && (s_axis_tlast == 1'b1) && (packet == 1'b1))
        packet <= 1'b0;
      else  
        packet <= packet;

      if ((s_axis_tvalid == 1'b1) && (s_axis_tready == 1'b1) && (packet != 1'b1))
        sop_o <= 1'b1;
      else 
        sop_o <= 1'b0;
      
      if ((s_axis_tlast == 1'b1) && (s_axis_tvalid == 1'b1) && (packet == 1'b1))
        eop_o <= 1'b1;
      else
        eop_o <= 1'b0; 

      // Set other signals (UNUSED FOR NOW)
      control_o <= 1'b0;
      err_o <= 1'b0;
    end 
  end

  // Dump waves
  /* initial begin */
  /*   $dumpfile("dump.vcd"); */
  /*   $dumpvars(1, ext_fifo_tx); */
  /* end */


endmodule

tests/tx_test/dump.vcd
$date
	Mon Aug 28 12:44:10 2023
$end
$version
	Icarus Verilog
$end
$timescale
	1ps
$end
$scope module ext_fifo_tx $end
$var wire 1 ! clk $end
$var wire 8 " data_o [7:0] $end
$var wire 1 # dma_tx_end_tog_i $end
$var wire 1 $ rd_i $end
$var wire 1 % rstn $end
$var wire 8 & s_axis_tdata [7:0] $end
$var wire 8 ' s_axis_tdest [7:0] $end
$var wire 8 ( s_axis_tid [7:0] $end
$var wire 1 ) s_axis_tkeep $end
$var wire 1 * s_axis_tlast $end
$var wire 1 + s_axis_tready $end
$var wire 1 , s_axis_tuser $end
$var wire 1 - s_axis_tvalid $end
$var wire 4 . status_i [3:0] $end
$var reg 1 / control_o $end
$var reg 1 0 data_ready_o $end
$var reg 1 1 data_valid_o $end
$var reg 1 2 dma_tx_status_tog_o $end
$var reg 1 3 eop_o $end
$var reg 1 4 err_o $end
$var reg 1 5 flushed_o $end
$var reg 1 6 packet $end
$var reg 1 7 sop_o $end
$var reg 1 8 underflow_o $end
$upscope $end
$enddefinitions $end
$comment Show the parameter values. $end
$dumpall
$end
#0
$dumpvars
08
07
x6
05
04
03
02
01
00
0/
b0 .
0-
z,
0+
0*
z)
bz (
bz '
b0 &
0%
0$
1#
b0 "
1!
$end
#5000
0!
#10000
1%
06
1!
#15000
0!
#20000
12
1!
#25000
0!
#30000
1!
#35000
0!
#40000
1!
#45000
0!
#50000
1!
#55000
0!
#60000
1!
#65000
0!
#70000
1!
#75000
0!
#80000
1!
#85000
0!
#90000
1!
#95000
0!
#100000
1-
1!
#105000
0!
#110000
10
1!
#115000
0!
#120000
1+
1$
1!
#125000
0!
#130000
b10101001 "
b10101001 &
17
16
11
1!
#135000
0!
#140000
b11100100 "
b11100100 &
07
00
1!
#145000
0!
#150000
0+
0$
b10011 "
b10011 &
1!
#155000
0!
#160000
01
1!
